shamira/__init__.py
shamira/__main__.py
shamira/benchmark.py
shamira/cli.py
shamira/core.py
shamira/fft.py
shamira/gf256.py
shamira/polynomial.py
shamira/util.py
shamira/version.py
shamira/tests/__init__.py
shamira/tests/test_fft.py
shamira/tests/test_gf256.py
shamira/tests/test_shamira.py
shamira-1.0.dist-info/LICENSE
shamira-1.0.dist-info/METADATA
shamira-1.0.dist-info/WHEEL
shamira-1.0.dist-info/entry_points.txt
shamira-1.0.dist-info/top_level.txt
shamira-1.0.dist-info/RECORD
