Metadata-Version: 2.1
Name: shamira
Version: 1.0
Summary: Shamir's secret sharing implementation. Splitting and joining secrets.
Home-page: https://repo.19x19.cz/Shamira
Author: Tadeáš Berkman
License: GPLv3
Project-URL: Issue Tracker, https://trac.19x19.cz/shamira/report
Platform: UNKNOWN
Classifier: Topic :: Security :: Cryptography
Classifier: License :: OSI Approved :: GNU General Public License v3 (GPLv3)
Requires-Python: >=3.6
License-File: LICENSE
